alibabacloud_tea_openapi_sse/__init__.py
alibabacloud_tea_openapi_sse/client.py
alibabacloud_tea_openapi_sse/models.py
alibabacloud_tea_openapi_sse-1.0.3.dist-info/METADATA
alibabacloud_tea_openapi_sse-1.0.3.dist-info/WHEEL
alibabacloud_tea_openapi_sse-1.0.3.dist-info/top_level.txt
alibabacloud_tea_openapi_sse-1.0.3.dist-info/RECORD
