Metadata-Version: 2.4
Name: alibabacloud_tea_openapi_sse
Version: 1.0.3
Summary: Alibaba Cloud openapi SDK Library for Python
Home-page: https://github.com/aliyun/darabonba-openapi
Author: Alibaba Cloud SDK
Author-email: sdk-team@alibabacloud.com
License: Apache License 2.0
Keywords: alibabacloud,tea,openapi
Platform: any
Classifier: Development Status :: 4 - Beta
Classifier: Intended Audience :: Developers
Classifier: License :: OSI Approved :: Apache Software License
Classifier: Programming Language :: Python
Classifier: Programming Language :: Python :: 3
Classifier: Programming Language :: Python :: 3.6
Classifier: Programming Language :: Python :: 3.7
Classifier: Programming Language :: Python :: 3.8
Classifier: Programming Language :: Python :: 3.9
Classifier: Topic :: Software Development
Requires-Python: >=3.6
Requires-Dist: alibabacloud_tea_sse<2.0.0,>=1.0.3
Requires-Dist: alibabacloud_tea_util_sse<2.0.0,>=1.0.1
Requires-Dist: alibabacloud_credentials>=0.3.6
Requires-Dist: alibabacloud_openapi_util<1.0.0,>=0.2.1
Requires-Dist: alibabacloud_gateway_spi<1.0.0,>=0.0.1
Requires-Dist: alibabacloud_tea_xml<1.0.0,>=0.0.2
Requires-Dist: aiohttp<4.0.0,>=3.7.0
Dynamic: author
Dynamic: author-email
Dynamic: classifier
Dynamic: description
Dynamic: description-content-type
Dynamic: home-page
Dynamic: keywords
Dynamic: license
Dynamic: platform
Dynamic: requires-dist
Dynamic: requires-python
Dynamic: summary
